setup.py
src/bold/__init__.py
src/bold/builders.py
src/bold/util.py
src/bold.egg-info/PKG-INFO
src/bold.egg-info/SOURCES.txt
src/bold.egg-info/dependency_links.txt
src/bold.egg-info/entry_points.txt
src/bold.egg-info/not-zip-safe
src/bold.egg-info/top_level.txt
src/bold/tests/__init__.py