Metadata-Version: 1.1
Name: bold
Version: 0.3
Summary: A software build automation tool
Home-page: https://github.com/fillest/bold
Author: Philipp Saveliev
Author-email: fsfeel@gmail.com
License: The MIT License (http://www.opensource.org/licenses/mit-license.php)
Platform: UNKNOWN
Classifier: Development Status :: 4 - Beta
Classifier: License :: OSI Approved :: MIT License
Classifier: Programming Language :: Python
Classifier: Intended Audience :: Developers
Classifier: Topic :: Software Development :: Build Tools
Classifier: Topic :: Utilities
Classifier: Environment :: Console
